diet_video/__init__.py
diet_video/__main__.py
diet_video/main.py
diet_video/patch_ffprobe.py
diet_video/utils.py
diet_video-0.1.14rc0.dist-info/entry_points.txt
diet_video-0.1.14rc0.dist-info/LICENSE
diet_video-0.1.14rc0.dist-info/WHEEL
diet_video-0.1.14rc0.dist-info/METADATA
diet_video-0.1.14rc0.dist-info/RECORD
